Workbook

Sheet 📖 Léeme
A1: 📗 DONNA — Planilla canónica (Vida + Finanzas unificadas)
A4: LA REGLA DE ORO | B4: Esta planilla NO se llena a mano. Donna escribe aquí; tú solo la miras.
A5: Tu interfaz es Telegram | B5: Brief 8:00 (solo lectura) + Cierre 22:00 (toques). Revisión los domingos.
A7: HOJAS DE VIDA
A8: Diario | B8: 1 fila/día: hábitos, ánimo (1-4), sueño, MITs. Nace vacía y crece con tu racha.
A9: Tareas | B9: Tareas sueltas y MITs. Por chat: 'tarea: ...'.
A10: Proyectos | B10: Tus 5 frentes. Esto SÍ lo editas tú (celdas amarillas).
A11: Recordatorios | B11: Escalera: domingo + 2 días antes + el día + insiste si vence. Estado: pendiente/hecho/pospuesto.
A12: Reconciliacion | B12: Plan vs. real: cada noche marcas qué hiciste y si tomó más/igual/menos. La escribe el bot con tus toques.
A13: Semanal | B13: Resumen del domingo: rachas, ánimo, gasto y TIEMPO POR FRENTE + tu factor de optimismo. Solo lectura.
A14: Ideas | B14: Captura por chat: 'idea: ...'. Se revisan el domingo.
A15: ⚙️ Config | B15: Horas, hábitos, módulos activos y tus frentes. Editable.
A17: HOJAS DE FINANZAS
A18: Transacciones | B18: Base de datos del dinero. El bot escribe aquí tras tu visto bueno en el digest.
A19: Categorias | B19: Única fuente de presupuestos. Agrega categorías cuando quieras.
A20: Tarjetas y Deuda | B20: El faro: tu DEUDA REAL incluye la línea de crédito. Intereses muertos = lo que pagas y no baja.
A21: Dashboard | B21: De un vistazo: ingresos, gastos, balance, tasa de ahorro, gasto por categoría.
A22: Comparativo | B22: Este mes vs. el anterior.
A24: CÓDIGO DE COLORES
A25: Amarillo | B25: Lo editas tú (Config, Proyectos, inputs de tarjetas).
A26: Encabezado verde | B26: Hojas de vida. Encabezado azul: finanzas.
A27: Todo lo demás | B27: Lo escribe o calcula el bot — no lo toques.
A29: NOTA DE MIGRACIÓN | B29: Recordatorios y proyectos vienen de Vida_v6 al nuevo esquema; verifica que estén tus 9 recordatorios. Las filas de Transacciones son ejemplos borrables.

Sheet Diario
A1: 🌙 DIARIO — 1 fila/día (la escribe el bot en el cierre). Ánimo: 1=😫 2=😐 3=🙂 4=🔥
A2: Fecha | B2: Ejercicio | C2: Meditación | D2: Última comida | E2: Sueño 7h+ | F2: Ánimo (1-4) | G2: Hora dormí | H2: MITs de mañana | I2: Brief ✓ | J2: Cierre ✓ | K2: Excepción | L2: Notas

Sheet Tareas
A1: ✅ TAREAS — sueltas y MITs. Por chat: 'tarea: ...'
A2: Creada | B2: Descripción | C2: Proyecto | D2: Tipo | E2: Fecha objetivo | F2: Estado | G2: Completada | H2: Notas
A4: 46185 | B4: Agendar revisión técnica camioneta (ejemplo real, ¡hazla!) | C4: — | D4: Tarea | E4: 46193 | F4: Pendiente | H4: Vence en junio ⚠️

Sheet Proyectos
A1: 🚀 PROYECTOS — tus frentes. Editas tú (amarillo); el bot marca avance.
A2: Proyecto | B2: Estado | C2: Foco actual | D2: Próxima acción | E2: % Avance | F2: Última act. | G2: Notas
A4: Tesis | B4: Activo | C4: Pruebas de laboratorio + escritura | D4: (define tu próxima acción) | E4: 0 | F4: 46185 | G4: Prioridad #4 según tu ranking
A5: Noomi Cookies | B5: Activo | C5: Operación del emprendimiento | D5: (define tu próxima acción) | E5: 0 | F5: 46185
A6: Monetizar Noomi | B6: Activo | C6: Vender Excel ERP + Bot a pastelerías | D6: (define tu próxima acción) | E6: 0.05 | F6: 46185 | G6: Prioridad #3
A7: Delivery | B7: Activo | C7: Ingresos fin de semana (Uber Eats) | D7: — | E7: 1 | F7: 46185 | G7: Meta $50k/semana
A8: Sistema Personal | B8: Activo | C8: Construcción bot Donna | D8: Deploy Fase 1 en Railway | E8: 0.1 | F8: 46185 | G8: F0 completada

Sheet Recordatorios
A1: 🔔 RECORDATORIOS — escalera: domingo + T-2 + T-0 + insiste si vence.
A2: Recordatorio | B2: Tipo | C2: Día / Fecha | D2: Monto aprox | E2: Estado | F2: Posposiciones | G2: Última acción | H2: Activo
A4: Pago contadora | B4: Mensual | C4: 1 | E4: Pendiente | F4: 0 | H4: Sí
A5: Pago IVA | B5: Mensual | C5: 1 | E5: Pendiente | F5: 0 | H5: Sí
A6: Cumple mes pareja 💕 | B6: Mensual | C6: 2 | E6: Pendiente | F6: 0 | H6: Sí
A7: Pago luz | B7: Mensual | C7: 10 | E7: Pendiente | F7: 0 | H7: Sí
A8: Pago niñera | B8: Mensual | C8: 10 | E8: Pendiente | F8: 0 | H8: Sí
A9: Aniversario pareja 💍 | B9: Anual | C9: 2026-05-02 | E9: Pendiente | F9: 0 | H9: Sí
A10: Cumpleaños pareja 🎂 | B10: Anual | C10: 2026-05-26 | E10: Pendiente | F10: 0 | H10: Sí
A11: Revisión técnica camioneta | B11: Única | C11: 2026-06-30 | E11: Pendiente | F11: 0 | H11: Sí
A12: (verifica tu 9° recordatorio de Vida_v6) | B12: Mensual | E12: Pendiente | F12: 0 | H12: Sí

Sheet Reconciliacion
A1: ⏱️ RECONCILIACIÓN — plan vs. real (la escribe el bot en el cierre con tus toques).
A2: Fecha | B2: Bloque / Evento | C2: Frente | D2: Min planeados | E2: ¿Hecho? | F2: Delta | G2: Min reales | H2: Notas
H3: Frente ∈ {Tesis, Noomi, Delivery, Hijo, Personal}. Delta ∈ {Menos, Igual, Más}. Alimenta el tiempo-por-frente del Semanal y el factor de optimismo.

Sheet Semanal
A1: 📊 SEMANAL — lo genera el bot el domingo. Solo lectura.
A2: Semana (lunes) | B2: Cierres /7 | C2: Briefs /7 | D2: 🏃 /7 | E2: 🧘 /7 | F2: 😴 /7 | G2: Ayuno /7 | H2: Ánimo prom | I2: Gasto semana | J2: h Tesis | K2: h Noomi | L2: h Delivery | M2: h Hijo | N2: Factor optimismo | O2: Meta semana | P2: ¿Cumplida? | Q2: 👶 Tiempo hijo

Sheet ⚙️ Config
A1: ⚙️ CONFIGURACIÓN — el bot lee esto al arrancar. Amarillo = editable.
A2: Parámetro | B2: Valor | C2: Nota
A4: Hora del brief | B4: 08:00 | C4: Arranque del día, solo lectura
A5: Hora del cierre | B5: 22:00 | C5: Ancla para estar en cama a las 23:00
A6: Día de revisión semanal | B6: Domingo | C6: El cierre se extiende con el resumen
A7: Hábitos del cierre | B7: Ejercicio, Meditación, Última comida | C7: Botones a las 22:00
A8: Hábito del brief | B8: Sueño 7h+ | C8: Se pregunta a las 8:00
A9: Meta hora de dormir | B9: 23:00 | C9: Tu objetivo (hoy ~1:00)
A10: Telegram Chat ID | B10: (llenar) | C10: El bot solo te responde a ti
A11: Mes activo | B11: 6 | C11: 1-12. Filtra Dashboard y Comparativo
A12: Año activo | B12: 2026 | C12: AAAA
A13: Frentes (reconciliación) | B13: Tesis, Noomi, Delivery, Hijo, Personal | C13: Categorías de tiempo
A14: Módulo Aprendizaje | B14: ON | C14: Calibra inferencias + factor de optimismo
A15: Módulo Proactividad | B15: ON | C15: Máx 1 mensaje espontáneo/día (12:00)
A16: Módulo Tiempo (log diario) | B16: OFF | C16: Dormido. Se promueve si el sistema lleva semanas vivo
A17: Correo Outlook | B17: OFF | C17: Descartado: tu banco va a Gmail / correo dedicado
A18: Correo: spam | B18: Archivar (etiqueta Donna/Archivado) | C18: JAMÁS borra — solo etiqueta, recuperable
A19: Correo: triage | B19: 3 buckets (spam/importante/financiero) | C19: Importantes → resumen brief; financieros → digest

Sheet Transacciones
A1: 💰 TRANSACCIONES — base del dinero. El bot escribe aquí tras tu visto bueno.
A2: Fecha | B2: Tipo | C2: Categoría | D2: Subcategoría | E2: Comercio | F2: Monto | G2: Medio | H2: Fuente | I2: ID_Único | J2: Intención
A4: 46174 | B4: Gasto | C4: Alimentación | D4: Supermercado | E4: Unimarc Las Condes | F4: 38500 | G4: Banco de Chile | H4: email_auto | I4: 2026-06-01_38500_Unimarc
A5: 46174 | B5: Gasto | C5: Transporte | D5: Taxi/Uber | E5: Uber al centro | F5: 4200 | G5: Mach | H5: manual | I5: 2026-06-01_4200_Uber
A6: 46175 | B6: Gasto | C6: Salud | D6: Farmacia | E6: Cruz Verde | F6: 12990 | G6: Banco de Chile | H6: foto | I6: 2026-06-02_12990_CruzVerde
A7: 46178 | B7: Ingreso | C7: Freelance | D7: Proyecto | E7: Pago cliente web | F7: 350000 | G7: Banco de Chile | H7: email_auto | I7: 2026-06-05_350000_Pago
A8: 46178 | B8: Gasto | C8: Suscripciones | D8: Streaming | E8: Netflix | F8: 8990 | G8: Banco de Chile | H8: email_auto | I8: 2026-06-05_8990_Netflix

Sheet Categorias
A1: 🏷️ CATEGORÍAS — única fuente de presupuestos.
A2: Categoría | B2: Tipo | C2: Presupuesto Mensual | D2: Notas
A4: Alimentación | B4: Gasto | C4: 250000 | D4: Super, minimarket
A5: Chanchería | B5: Gasto | C5: 30000 | D5: Delivery, antojos
A6: Transporte | B6: Gasto | C6: 50000 | D6: Bencina, Uber, micro
A7: Salud | B7: Gasto | C7: 20000 | D7: Farmacia, médico, suplementos
A8: Hijo | B8: Gasto | C8: 0 | D8: Pañales, ropa, salud, educación
A9: Entretenimiento | B9: Gasto | C9: 40000 | D9: Salidas, asados
A10: Suscripciones | B10: Gasto | C10: 0 | D10: Netflix, Spotify
A11: Ropa | B11: Gasto | C11: 0
A12: Hogar | B12: Gasto | C12: 80000 | D12: Limpieza, gastos hogar
A13: GGCC | B13: Gasto | C13: 120000 | D13: Luz, agua, gas, internet
A14: Educación | B14: Gasto | C14: 0 | D14: Cursos, libros
A15: Tecnología | B15: Gasto | C15: 28000 | D15: Gadgets, software, APIs
A16: Tarjeta Crédito | B16: Gasto | C16: 0 | D16: Pago de tarjeta
A17: Otro Gasto | B17: Gasto | C17: 0 | D17: Sin clasificar
A18: Freelance | B18: Ingreso | C18: 0 | D18: Proyectos independientes
A19: Ayuda Familiar | B19: Ingreso | C19: 0 | D19: Ayuda padres
A20: Uber Eats | B20: Ingreso | C20: 0 | D20: Reparto en moto
A21: Clases | B21: Ingreso | C21: 0 | D21: Clases particulares

Sheet Metas
A1: 🎯 METAS — tus metas de plata. Fija el Objetivo; Donna actualiza Actual/Progreso cuando aportas.
A2: Meta | B2: Objetivo | C2: Actual | D2: Progreso | E2: Notas

Sheet Compras_Detalle
A1: 🧾 COMPRAS_DETALLE — el detalle ítem-a-ítem de una compra (v3). Una transacción de Transacciones puede tener varias líneas acá (ID_Tx = ID_Único del padre).
A2: Fecha | B2: Comercio | C2: Item | D2: Cantidad | E2: Precio | F2: Categoría | G2: Intención | H2: Predecible | I2: ID_Tx | J2: Fuente

Sheet Tarjetas y Deuda
A1: 💳 TARJETAS Y DEUDA — tu deuda REAL incluye la línea de crédito.
A3: 🔦 FARO DE DEUDA
A4: DEUDA TOTAL REAL (tarjetas + línea) | B4: =B29+B40+B44
A5: INTERESES MUERTOS DEL MES | B5: =B25+B37+B45
A6: % Utilización total | B6: =(B29+B40+B44)/(B28+B39+B43)
A7: Semáforo | B7: =IF(B6>0.7,"🔴 Alto",IF(B6>0.3,"🟡 Medio","🟢 OK"))
A8: TOTAL A PAGAR ESTE MES | B8: =B27+B38+B45
A9: La línea + el rotativo es la fuga: pagas y la deuda no baja.
A19: 🏦 BANCO DE CHILE
A20: Tasa mensual | B20: 0.0273
A21: Deuda rotativa actual | B21: 667993
A22: Pago este mes | B22: 50000
A23: Mantención mensual | B23: 6061
A24: Total cuotas del mes | B24: 65861
A25: → Interés del mes | B25: =B20*B21
A26: → Deuda rotativa próx. mes | B26: =MAX(0,B21+B25-B22)
A27: Total a pagar (BCh) | B27: =B24+B22+B23
A28: Cupo total | B28: 1000000
A29: Deuda total tarjeta (rotativo+cuotas pend.) | B29: 859437
A31: 📱 MACH
A32: Tasa mensual | B32: 0
A33: Deuda rotativa actual | B33: 0
A34: Pago este mes | B34: 0
A35: Mantención mensual | B35: 5257
A36: Total cuotas del mes | B36: 43114
A37: → Interés del mes | B37: =B32*B33
A38: Total a pagar (Mach) | B38: =B36+B34+B35
A39: Cupo total | B39: 300000
A40: Deuda total tarjeta (rotativo+cuotas pend.) | B40: 168654
A42: 🏦 LÍNEA DE CRÉDITO
A43: Cupo total | B43: 1000000
A44: Monto utilizado | B44: 1000000
A45: Interés mensual que pagas | B45: 30000
A46: → Tasa mensual implícita | B46: =IF(B44>0,B45/B44,0)
A47: → Disponible | B47: =B43-B44

Sheet Dashboard
A1: 📈 DASHBOARD — del mes activo (ajusta Mes/Año abajo).
D2: Mes activo | E2: 6 | F2: Año | G2: 2026
A4: Ingresos del mes | B4: =SUMIFS(Transacciones!F:F,Transacciones!B:B,"Ingreso",Transacciones!A:A,">="&DATE($G$2,$E$2,1),Transacciones!A:A,"<="&EOMONTH(DATE($G$2,$E$2,1),0))
A5: Gastos del mes | B5: =SUMIFS(Transacciones!F:F,Transacciones!B:B,"Gasto",Transacciones!A:A,">="&DATE($G$2,$E$2,1),Transacciones!A:A,"<="&EOMONTH(DATE($G$2,$E$2,1),0))
A6: Balance | B6: =B4-B5
A7: Tasa de ahorro | B7: =IF(B4>0,B6/B4,"-")
A8: ¿Llego a fin de mes? | B8: =IF(B6>=0,"Te sobran $"&TEXT(B6,"#,##0"),"Negativo por $"&TEXT(-B6,"#,##0"))
A10: GASTO POR CATEGORÍA
A11: Categoría | B11: Presupuesto | C11: Gastado | D11: % Usado
A12: =Categorias!A3 | B12: =Categorias!C3 | C12: =SUMIFS(Transacciones!F:F,Transacciones!C:C,Categorias!A3,Transacciones!B:B,"Gasto",Transacciones!A:A,">="&DATE($G$2,$E$2,1),Transacciones!A:A,"<="&EOMONTH(DATE($G$2,$E$2,1),0)) | D12: =IF(Categorias!C3>0,C12/B12,"-")
A13: =Categorias!A4 | B13: =Categorias!C4 | C13: =SUMIFS(Transacciones!F:F,Transacciones!C:C,Categorias!A4,Transacciones!B:B,"Gasto",Transacciones!A:A,">="&DATE($G$2,$E$2,1),Transacciones!A:A,"<="&EOMONTH(DATE($G$2,$E$2,1),0)) | D13: =IF(Categorias!C4>0,C13/B13,"-")
A14: =Categorias!A5 | B14: =Categorias!C5 | C14: =SUMIFS(Transacciones!F:F,Transacciones!C:C,Categorias!A5,Transacciones!B:B,"Gasto",Transacciones!A:A,">="&DATE($G$2,$E$2,1),Transacciones!A:A,"<="&EOMONTH(DATE($G$2,$E$2,1),0)) | D14: =IF(Categorias!C5>0,C14/B14,"-")
A15: =Categorias!A6 | B15: =Categorias!C6 | C15: =SUMIFS(Transacciones!F:F,Transacciones!C:C,Categorias!A6,Transacciones!B:B,"Gasto",Transacciones!A:A,">="&DATE($G$2,$E$2,1),Transacciones!A:A,"<="&EOMONTH(DATE($G$2,$E$2,1),0)) | D15: =IF(Categorias!C6>0,C15/B15,"-")
A16: =Categorias!A7 | B16: =Categorias!C7 | C16: =SUMIFS(Transacciones!F:F,Transacciones!C:C,Categorias!A7,Transacciones!B:B,"Gasto",Transacciones!A:A,">="&DATE($G$2,$E$2,1),Transacciones!A:A,"<="&EOMONTH(DATE($G$2,$E$2,1),0)) | D16: =IF(Categorias!C7>0,C16/B16,"-")
A17: =Categorias!A8 | B17: =Categorias!C8 | C17: =SUMIFS(Transacciones!F:F,Transacciones!C:C,Categorias!A8,Transacciones!B:B,"Gasto",Transacciones!A:A,">="&DATE($G$2,$E$2,1),Transacciones!A:A,"<="&EOMONTH(DATE($G$2,$E$2,1),0)) | D17: =IF(Categorias!C8>0,C17/B17,"-")
A18: =Categorias!A9 | B18: =Categorias!C9 | C18: =SUMIFS(Transacciones!F:F,Transacciones!C:C,Categorias!A9,Transacciones!B:B,"Gasto",Transacciones!A:A,">="&DATE($G$2,$E$2,1),Transacciones!A:A,"<="&EOMONTH(DATE($G$2,$E$2,1),0)) | D18: =IF(Categorias!C9>0,C18/B18,"-")
A19: =Categorias!A10 | B19: =Categorias!C10 | C19: =SUMIFS(Transacciones!F:F,Transacciones!C:C,Categorias!A10,Transacciones!B:B,"Gasto",Transacciones!A:A,">="&DATE($G$2,$E$2,1),Transacciones!A:A,"<="&EOMONTH(DATE($G$2,$E$2,1),0)) | D19: =IF(Categorias!C10>0,C19/B19,"-")
A20: =Categorias!A11 | B20: =Categorias!C11 | C20: =SUMIFS(Transacciones!F:F,Transacciones!C:C,Categorias!A11,Transacciones!B:B,"Gasto",Transacciones!A:A,">="&DATE($G$2,$E$2,1),Transacciones!A:A,"<="&EOMONTH(DATE($G$2,$E$2,1),0)) | D20: =IF(Categorias!C11>0,C20/B20,"-")
A21: =Categorias!A12 | B21: =Categorias!C12 | C21: =SUMIFS(Transacciones!F:F,Transacciones!C:C,Categorias!A12,Transacciones!B:B,"Gasto",Transacciones!A:A,">="&DATE($G$2,$E$2,1),Transacciones!A:A,"<="&EOMONTH(DATE($G$2,$E$2,1),0)) | D21: =IF(Categorias!C12>0,C21/B21,"-")
A22: =Categorias!A13 | B22: =Categorias!C13 | C22: =SUMIFS(Transacciones!F:F,Transacciones!C:C,Categorias!A13,Transacciones!B:B,"Gasto",Transacciones!A:A,">="&DATE($G$2,$E$2,1),Transacciones!A:A,"<="&EOMONTH(DATE($G$2,$E$2,1),0)) | D22: =IF(Categorias!C13>0,C22/B22,"-")
A23: =Categorias!A14 | B23: =Categorias!C14 | C23: =SUMIFS(Transacciones!F:F,Transacciones!C:C,Categorias!A14,Transacciones!B:B,"Gasto",Transacciones!A:A,">="&DATE($G$2,$E$2,1),Transacciones!A:A,"<="&EOMONTH(DATE($G$2,$E$2,1),0)) | D23: =IF(Categorias!C14>0,C23/B23,"-")
... A29: =Categorias!A20 | B29: =Categorias!C20 | C29: =SUMIFS(Transacciones!F:F,Transacciones!C:C,Categorias!A20,Transacciones!B:B,"Gasto",Transacciones!A:A,">="&DATE($G$2,$E$2,1),Transacciones!A:A,"<="&EOMONTH(DATE($G$2,$E$2,1),0)) | D29: =IF(Categorias!C20>0,C29/B29,"-")

Sheet Comparativo
A1: 🔁 COMPARATIVO — mes activo vs. anterior.
A2: Concepto | B2: Mes activo | C2: Mes anterior | D2: Variación
A3: Ingresos | B3: =SUMIFS(Transacciones!F:F,Transacciones!B:B,"Ingreso",Transacciones!A:A,">="&DATE(Dashboard!$G$2,Dashboard!$E$2,1),Transacciones!A:A,"<="&EOMONTH(DATE(Dashboard!$G$2,Dashboard!$E$2,1),0)) | C3: =SUMIFS(Transacciones!F:F,Transacciones!B:B,"Ingreso",Transacciones!A:A,">="&EOMONTH(DATE(Dashboard!$G$2,Dashboard!$E$2,1),-2)+1,Transacciones!A:A,"<="&EOMONTH(DATE(Dashboard!$G$2,Dashboard!$E$2,1),-1)) | D3: =IF(C3>0,(B3-C3)/C3,"-")
A4: Gastos | B4: =SUMIFS(Transacciones!F:F,Transacciones!B:B,"Gasto",Transacciones!A:A,">="&DATE(Dashboard!$G$2,Dashboard!$E$2,1),Transacciones!A:A,"<="&EOMONTH(DATE(Dashboard!$G$2,Dashboard!$E$2,1),0)) | C4: =SUMIFS(Transacciones!F:F,Transacciones!B:B,"Gasto",Transacciones!A:A,">="&EOMONTH(DATE(Dashboard!$G$2,Dashboard!$E$2,1),-2)+1,Transacciones!A:A,"<="&EOMONTH(DATE(Dashboard!$G$2,Dashboard!$E$2,1),-1)) | D4: =IF(C4>0,(B4-C4)/C4,"-")
A5: Balance | B5: =B3-B4 | C5: =C3-C4
